aliexpress_api/__init__.py
aliexpress_api/api.py
aliexpress_api/errors/__init__.py
aliexpress_api/errors/exceptions.py
aliexpress_api/helpers/__init__.py
aliexpress_api/helpers/arguments.py
aliexpress_api/helpers/categories.py
aliexpress_api/helpers/products.py
aliexpress_api/helpers/requests.py
aliexpress_api/models/__init__.py
aliexpress_api/models/affiliate_link.py
aliexpress_api/models/category.py
aliexpress_api/models/currencies.py
aliexpress_api/models/hotproducts.py
aliexpress_api/models/languages.py
aliexpress_api/models/product.py
aliexpress_api/models/request_parameters.py
aliexpress_api/skd/__init__.py
aliexpress_api/skd/api/__init__.py
aliexpress_api/skd/api/base.py
aliexpress_api/skd/api/rest/AliexpressAffiliateCategoryGetRequest.py
aliexpress_api/skd/api/rest/AliexpressAffiliateFeaturedpromoGetRequest.py
aliexpress_api/skd/api/rest/AliexpressAffiliateFeaturedpromoProductsGetRequest.py
aliexpress_api/skd/api/rest/AliexpressAffiliateHotproductDownloadRequest.py
aliexpress_api/skd/api/rest/AliexpressAffiliateHotproductQueryRequest.py
aliexpress_api/skd/api/rest/AliexpressAffiliateLinkGenerateRequest.py
aliexpress_api/skd/api/rest/AliexpressAffiliateOrderGetRequest.py
aliexpress_api/skd/api/rest/AliexpressAffiliateOrderListRequest.py
aliexpress_api/skd/api/rest/AliexpressAffiliateOrderListbyindexRequest.py
aliexpress_api/skd/api/rest/AliexpressAffiliateProductQueryRequest.py
aliexpress_api/skd/api/rest/AliexpressAffiliateProductSmartmatchRequest.py
aliexpress_api/skd/api/rest/AliexpressAffiliateProductdetailGetRequest.py
aliexpress_api/skd/api/rest/__init__.py
aliexpress_api/tools/__init__.py
aliexpress_api/tools/get_product_id.py
python_aliexpress_api-3.0.0.dist-info/LICENSE
python_aliexpress_api-3.0.0.dist-info/METADATA
python_aliexpress_api-3.0.0.dist-info/WHEEL
python_aliexpress_api-3.0.0.dist-info/top_level.txt
python_aliexpress_api-3.0.0.dist-info/RECORD
