Metadata-Version: 2.1
Name: python-aliexpress-api
Version: 3.0.0
Summary: AliExpress API wrapper for Python
Home-page: https://github.com/sergioteula/python-aliexpress-api
Author: Sergio Abad
Author-email: sergio.abad@bytelix.com
License: MIT
Classifier: Programming Language :: Python
Classifier: License :: OSI Approved :: MIT License
Classifier: Operating System :: OS Independent
Requires-Python: >=3.6
License-File: LICENSE
